korsair/__init__.py
korsair/korsair.py
korsair-1.0.5.dist-info/LICENSE
korsair-1.0.5.dist-info/METADATA
korsair-1.0.5.dist-info/WHEEL
korsair-1.0.5.dist-info/top_level.txt
korsair-1.0.5.dist-info/RECORD
