Metadata-Version: 2.1
Name: korsair
Version: 1.0.5
Summary: korsair pythonlib release
Home-page: UNKNOWN
Author: ksb98
Author-email: qkfka9045@gmail.com
License: MIT
Platform: UNKNOWN
Requires-Python: >=3
Requires-Dist: requests
Requires-Dist: pandas
